<?xml version="1.0" encoding="UTF-8"?>
<rdf:RDF xmlns:dcterms="http://purl.org/dc/terms/"
         xmlns:pc="http://purl.org/procurement/public-contracts#"
         xmlns:gr="http://purl.org/goodrelations/v1#"
         xmlns:rdf="http://www.w3.org/1999/02/22-rdf-syntax-ns#"
         xmlns:s="http://schema.org/"
         xmlns:pceu="http://purl.org/procurement/public-contracts-eu#"
         xmlns:xsd="http://www.w3.org/2001/XMLSchema"
         xmlns:skos="http://www.w3.org/2004/02/skos/core#"
         xmlns:adms="http://www.w3.org/ns/adms#"
         xmlns:pproc="http://contsem.unizar.es/def/sector-publico/pproc#"
         xmlns:ProcurementRegulations="https://loted2.googlecode.com/svn/trunk/modules/ProcurementRegulations#"
         xmlns:TenderDocuments="https://loted2.googlecode.com/svn/trunk/modules/TenderDocuments#"
         xmlns:foaf="http://xmlns.com/foaf/0.1/">
   <pc:ContractNotice rdf:about="http://linked.opendata.cz/resource/ted.europa.eu/contract-notice/001185-2015">
      <pc:publicationDate rdf:datatype="http://www.w3.org/2001/XMLSchema#date">2015-01-02</pc:publicationDate>
   </pc:ContractNotice>
   <pc:Contract rdf:about="http://linked.opendata.cz/resource/ted.europa.eu/public-contract/001185-2015">
      <pc:publicNotice rdf:resource="http://linked.opendata.cz/resource/ted.europa.eu/contract-notice/001185-2015"/>
      <pc:contractingAuthority>
         <gr:BusinessEntity rdf:about="http://linked.opendata.cz/resource/ted.europa.eu/business-entity/6b31d196-f1d2-4348-a65a-b60a6796ddc1">
            <gr:legalName>Vattenfall Europe Netzservice GmbH</gr:legalName>
            <s:address>
               <s:PostalAddress rdf:about="http://linked.opendata.cz/resource/ted.europa.eu/postal-address/66de73bb-d2c6-46f1-968e-a485717c986b">
                  <s:streetAddress>Puschkinallee 52</s:streetAddress>
                  <s:addressLocality>Berlin</s:addressLocality>
                  <s:postalCode>12435</s:postalCode>
                  <s:addressCountry>DE</s:addressCountry>
               </s:PostalAddress>
            </s:address>
            <foaf:page rdf:datatype="http://www.w3.org/2001/XMLSchema#anyURI">www.vattenfall.de</foaf:page>
            <pc:mainActivity rdf:resource="http://purl.org/procurement/public-contracts-activities#Electricity"/>
         </gr:BusinessEntity>
      </pc:contractingAuthority>
      <pc:contact>
         <s:ContactPoint rdf:about="http://linked.opendata.cz/resource/ted.europa.eu/contact-point/78798ae4-428f-45d0-8c04-bdc41ca051f5">
            <s:description>Hrn. Stefan Riese</s:description>
            <s:telephone>+49 3026711086</s:telephone>
            <s:email>stefan.riese@vattenfall.de</s:email>
            <s:faxNumber>+49 3026711911086</s:faxNumber>
         </s:ContactPoint>
      </pc:contact>
      <pc:onBehalfOf>
         <s:Organization rdf:about="http://linked.opendata.cz/resource/ted.europa.eu/business-entity/a25ec64b-7e54-40a3-a121-4332a43822ea">
            <gr:legalName>Stromnetz Berlin GmbH</gr:legalName>
            <s:address>
               <s:PostalAddress rdf:about="http://linked.opendata.cz/resource/ted.europa.eu/postal-address/f372fae4-dde3-456d-a42d-4947e46c1d28">
                  <s:streetAddress>Puschkinallee 52</s:streetAddress>
                  <s:addressLocality>Berlin</s:addressLocality>
                  <s:postalCode>12435</s:postalCode>
                  <s:addressCountry>DE</s:addressCountry>
               </s:PostalAddress>
            </s:address>
         </s:Organization>
      </pc:onBehalfOf>
      <pc:onBehalfOf>
         <s:Organization rdf:about="http://linked.opendata.cz/resource/ted.europa.eu/business-entity/7254a45a-8a0b-4563-a316-a99557967117">
            <gr:legalName>Stromnetz Hamburg GmbH</gr:legalName>
            <s:address>
               <s:PostalAddress rdf:about="http://linked.opendata.cz/resource/ted.europa.eu/postal-address/417011ae-832f-433b-9b1e-1a003735081c">
                  <s:streetAddress>Bramfelder Chaussee 130</s:streetAddress>
                  <s:addressLocality>Hamburg</s:addressLocality>
                  <s:postalCode>22177</s:postalCode>
                  <s:addressCountry>DE</s:addressCountry>
               </s:PostalAddress>
            </s:address>
         </s:Organization>
      </pc:onBehalfOf>
      <dcterms:title xml:lang="DE">10-kV-Netzkompaktstationen.</dcterms:title>
      <pc:kind rdf:resource="http://purl.org/procurement/public-contracts-kinds#Supplies"/>
      <pc:mainObject rdf:resource="http://linked.opendata.cz/resource/cpv-2008/concept/45315300"/>
      <pc:additionalObject rdf:resource="http://linked.opendata.cz/resource/cpv-2008/concept/31230000"/>
      <pc:additionalObject rdf:resource="http://linked.opendata.cz/resource/cpv-2008/concept/31213000"/>
      <pc:additionalObject rdf:resource="http://linked.opendata.cz/resource/cpv-2008/concept/31213400"/>
      <pc:additionalObject rdf:resource="http://linked.opendata.cz/resource/cpv-2008/concept/31214000"/>
      <pc:additionalObject rdf:resource="http://linked.opendata.cz/resource/cpv-2008/concept/45317200"/>
      <TenderDocuments:covers>
         <ProcurementRegulations:GovernmentProcurementAgreement rdf:about="http://linked.opendata.cz/resource/ted.europa.eu/government-procurement-agreement/1"/>
      </TenderDocuments:covers>
      <pproc:ContractProcedureSpecification>
         <pproc:ElectronicAuction rdf:about="http://linked.opendata.cz/resource/ted.europa.eu/electronic-auction/1">
            <pproc:electronicAuction rdf:datatype="http://www.w3.org/2001/XMLSchema#boolean">false</pproc:electronicAuction>
         </pproc:ElectronicAuction>
      </pproc:ContractProcedureSpecification>
      <pc:notice>
         <pproc:ContractAwardNotice rdf:about="http://linked.opendata.cz/resource/ted.europa.eu/contract-notice/001185-2015">
            <pproc:noticeSentDate rdf:datatype="http://www.w3.org/2001/XMLSchema#date">2014-12-30</pproc:noticeSentDate>
         </pproc:ContractAwardNotice>
      </pc:notice>
   </pc:Contract>
</rdf:RDF>
